HashCode.py
LICENCE.txt
MANIFEST.in
changelog.txt
readme.txt
setup.py
HashCode.egg-info/PKG-INFO
HashCode.egg-info/SOURCES.txt
HashCode.egg-info/dependency_links.txt
HashCode.egg-info/top_level.txt