Metadata-Version: 2.1
Name: HashCode
Version: 0.0.4
Summary: A hashing library
Home-page: UNKNOWN
Author: Abderrahman Hiroual
Author-email: hiroual.abderrahman.student@gd-gsr.com
License: MIT
Keywords: Hashing
Platform: UNKNOWN
Classifier: Development Status :: 5 - Production/Stable
Classifier: Intended Audience :: Education
Classifier: Operating System :: Microsoft :: Windows :: Windows 10
Classifier: License :: OSI Approved :: MIT License
Classifier: Programming Language :: Python :: 3
